Metadata-Version: 2.1
Name: docker-detect
Version: 0.0.2
Summary: Detect whether the current process is running inside Docker/Kubernetes/LXC container
Home-page: https://github.com/agmarx/docker-detect
Author: agmarx
Author-email: agmarx@protonmail.com
License: UNKNOWN
Platform: UNKNOWN
Classifier: Programming Language :: Python :: 3
Classifier: License :: OSI Approved :: MIT License
Classifier: Operating System :: OS Independent
